observare_sdk/__init__.py
observare_sdk/config.py
observare_sdk/hallucination.py
observare_sdk/llm.py
observare_sdk/logging_config.py
observare_sdk/pii.py
observare_sdk/py.typed
observare_sdk/sdk.py
observare_sdk-1.0.6.dist-info/METADATA
observare_sdk-1.0.6.dist-info/WHEEL
observare_sdk-1.0.6.dist-info/top_level.txt
observare_sdk-1.0.6.dist-info/RECORD
