Metadata-Version: 2.4
Name: observare-sdk
Version: 1.0.6
Summary: Observability / Telemetry and Safety SDK for LangChain agents with PII redaction and hallucination detection
Author-email: Observare <support@observare.ai>
License: Proprietary
Project-URL: Homepage, https://observare.ai
Project-URL: Documentation, https://docs.observare.ai
Project-URL: Repository, https://github.com/observare-ai/observare-sdk
Project-URL: Issues, https://github.com/observare-ai/observare-sdk/issues
Classifier: Development Status :: 4 - Beta
Classifier: Intended Audience :: Developers
Classifier: Topic :: Software Development :: Libraries :: Python Modules
Classifier: Topic :: Scientific/Engineering :: Artificial Intelligence
Classifier: Programming Language :: Python :: 3
Classifier: Programming Language :: Python :: 3.8
Classifier: Programming Language :: Python :: 3.9
Classifier: Programming Language :: Python :: 3.10
Classifier: Programming Language :: Python :: 3.11
Classifier: Programming Language :: Python :: 3.12
Requires-Python: >=3.8
Requires-Dist: langchain>=0.1.0
Requires-Dist: langchain-openai>=0.1.0
Requires-Dist: langchain-community>=0.0.20
Requires-Dist: requests>=2.25.0
Requires-Dist: presidio-analyzer>=2.2.354
Requires-Dist: presidio-anonymizer>=2.2.354
Provides-Extra: dev
Requires-Dist: pytest>=7.0.0; extra == "dev"
Requires-Dist: pytest-asyncio>=0.21.0; extra == "dev"
Requires-Dist: black>=22.0.0; extra == "dev"
Requires-Dist: isort>=5.0.0; extra == "dev"
Requires-Dist: flake8>=4.0.0; extra == "dev"
Requires-Dist: mypy>=1.0.0; extra == "dev"
Provides-Extra: spacy
Requires-Dist: spacy>=3.4.0; extra == "spacy"
